{
  "run_id": 31,
  "trade_date": "2026-04-22",
  "source": "eastmoney",
  "signal_count": 10,
  "validation_count": 10,
  "paper_execution": {
    "enabled": true,
    "opened": [
      {
        "symbol": "301278",
        "name": "快可电子",
        "entry_price": 44.0,
        "target_weight_pct": 8.0
      }
    ],
    "closed": [
      {
        "symbol": "301278",
        "name": "快可电子",
        "exit_price": 44.0,
        "realized_return_pct": 0.0,
        "exit_reason": "paper_riskmode_exit"
      }
    ],
    "rebalanced": [],
    "opened_count": 1,
    "closed_count": 1,
    "rebalanced_count": 0,
    "execution_skipped": false,
    "execution_policy": "paper_only",
    "risk_mode": "defensive_probe",
    "market_stage": "ice",
    "summary": {
      "open_positions": 4,
      "closed_positions": 12,
      "open_weight_pct": 8.0,
      "unrealized_pnl_pct": 0.0,
      "realized_pnl_pct": 0.0,
      "total_pnl_pct": 0.0,
      "win_rate_pct": 0.0,
      "trade_count": 28
    },
    "positions": [
      {
        "id": 16,
        "symbol": "301278",
        "name": "快可电子",
        "opened_trade_date": "2026-04-22",
        "entry_price": 44.0,
        "target_weight_pct": 8.0,
        "status": "open",
        "theme": "半导体",
        "strategy_json": "[\"hotmoney\", \"leader\"]",
        "plan_json": "{\"symbol\": \"301278\", \"name\": \"快可电子\", \"display\": \"快可电子 (301278)\", \"theme\": \"半导体\", \"resonance_level\": \"A\", \"resonance_score\": 79.1, \"strategies\": [\"hotmoney\", \"leader\"], \"target_weight_pct\": 8.0, \"role\": \"follower\", \"thesis\": \"情绪阶段 ice / 题材热度排名 2 / 题材热度分 14.54\", \"sizing_meta\": {\"base_weight_pct\": 12.0, \"quality_multiplier\": 1.37, \"risk_discount\": 1.0, \"allowed_cap_pct\": 8.0}}",
        "created_at": "2026-04-22 13:14:28",
        "closed_trade_date": null,
        "exit_price": null,
        "realized_return_pct": null,
        "peak_return_pct": 0.0,
        "partial_exit_taken": 0,
        "lifecycle_state": "open"
      },
      {
        "id": 12,
        "symbol": "000004",
        "name": "盛景智能",
        "opened_trade_date": "2026-04-22",
        "entry_price": 22.11,
        "target_weight_pct": 8.0,
        "status": "open",
        "theme": "机器人",
        "strategy_json": "[\"hotmoney\", \"leader\"]",
        "plan_json": "{\"symbol\": \"000004\", \"name\": \"盛景智能\", \"display\": \"盛景智能 (000004)\", \"theme\": \"机器人\", \"resonance_level\": \"A\", \"resonance_score\": 100.0, \"strategies\": [\"hotmoney\", \"leader\"], \"target_weight_pct\": 8.0, \"role\": \"mainline_leader\", \"thesis\": \"情绪阶段 ice / 题材热度排名 1 / 题材热度分 2.62\", \"sizing_meta\": {\"base_weight_pct\": 12.0, \"quality_multiplier\": 1.26, \"risk_discount\": 1.0, \"allowed_cap_pct\": 8.0}}",
        "created_at": "2026-04-22 00:31:57",
        "closed_trade_date": null,
        "exit_price": null,
        "realized_return_pct": null,
        "peak_return_pct": 0.0,
        "partial_exit_taken": 0,
        "lifecycle_state": "open"
      },
      {
        "id": 11,
        "symbol": "300584",
        "name": "海辰药业",
        "opened_trade_date": "2026-03-27",
        "entry_price": 45.18,
        "target_weight_pct": 12.0,
        "status": "open",
        "theme": "医药",
        "strategy_json": "[\"hotmoney\", \"leader\"]",
        "plan_json": "{\"symbol\": \"300584\", \"name\": \"海辰药业\", \"display\": \"海辰药业 (300584)\", \"theme\": \"医药\", \"resonance_level\": \"A\", \"resonance_score\": 79.1, \"strategies\": [\"hotmoney\", \"leader\"], \"target_weight_pct\": 12, \"role\": \"follower\", \"thesis\": \"情绪阶段 ice / 题材热度排名 1 / 题材热度分 37.36\"}",
        "created_at": "2026-03-27 15:31:35",
        "closed_trade_date": null,
        "exit_price": null,
        "realized_return_pct": null,
        "peak_return_pct": 0.0,
        "partial_exit_taken": 0,
        "lifecycle_state": "open"
      },
      {
        "id": 5,
        "symbol": "301587",
        "name": "中瑞股份",
        "opened_trade_date": "2026-03-26",
        "entry_price": 27.03,
        "target_weight_pct": 12.0,
        "status": "open",
        "theme": "电力设备",
        "strategy_json": "[\"hotmoney\", \"leader\"]",
        "plan_json": "{\"symbol\": \"301587\", \"name\": \"中瑞股份\", \"display\": \"中瑞股份 (301587)\", \"theme\": \"电力设备\", \"resonance_level\": \"A\", \"resonance_score\": 79.1, \"strategies\": [\"hotmoney\", \"leader\"], \"target_weight_pct\": 12, \"role\": \"follower\", \"thesis\": \"情绪阶段 ice / 题材热度排名 1 / 题材热度分 12.7\"}",
        "created_at": "2026-03-26 13:25:46",
        "closed_trade_date": null,
        "exit_price": null,
        "realized_return_pct": null,
        "peak_return_pct": 0.0,
        "partial_exit_taken": 0,
        "lifecycle_state": "open"
      },
      {
        "id": 15,
        "symbol": "301278",
        "name": "快可电子",
        "opened_trade_date": "2026-04-22",
        "entry_price": 44.0,
        "target_weight_pct": 8.0,
        "status": "closed",
        "theme": "半导体",
        "strategy_json": "[\"hotmoney\", \"leader\"]",
        "plan_json": "{\"symbol\": \"301278\", \"name\": \"快可电子\", \"display\": \"快可电子 (301278)\", \"theme\": \"半导体\", \"resonance_level\": \"A\", \"resonance_score\": 79.1, \"strategies\": [\"hotmoney\", \"leader\"], \"target_weight_pct\": 8.0, \"role\": \"follower\", \"thesis\": \"情绪阶段 ice / 题材热度排名 2 / 题材热度分 14.54\", \"sizing_meta\": {\"base_weight_pct\": 12.0, \"quality_multiplier\": 1.26, \"risk_discount\": 1.0, \"allowed_cap_pct\": 8.0}}",
        "created_at": "2026-04-22 13:10:33",
        "closed_trade_date": "2026-04-22",
        "exit_price": 44.0,
        "realized_return_pct": 0.0,
        "peak_return_pct": 0.0,
        "partial_exit_taken": 0,
        "lifecycle_state": "open"
      },
      {
        "id": 14,
        "symbol": "301278",
        "name": "快可电子",
        "opened_trade_date": "2026-04-22",
        "entry_price": 44.0,
        "target_weight_pct": 8.0,
        "status": "closed",
        "theme": "半导体",
        "strategy_json": "[\"hotmoney\", \"leader\"]",
        "plan_json": "{\"symbol\": \"301278\", \"name\": \"快可电子\", \"display\": \"快可电子 (301278)\", \"theme\": \"半导体\", \"resonance_level\": \"A\", \"resonance_score\": 79.1, \"strategies\": [\"hotmoney\", \"leader\"], \"target_weight_pct\": 8.0, \"role\": \"follower\", \"thesis\": \"情绪阶段 ice / 题材热度排名 2 / 题材热度分 14.54\", \"sizing_meta\": {\"base_weight_pct\": 12.0, \"quality_multiplier\": 1.26, \"risk_discount\": 1.0, \"allowed_cap_pct\": 8.0}}",
        "created_at": "2026-04-22 13:08:23",
        "closed_trade_date": "2026-04-22",
        "exit_price": 44.0,
        "realized_return_pct": 0.0,
        "peak_return_pct": 0.0,
        "partial_exit_taken": 0,
        "lifecycle_state": "open"
      },
      {
        "id": 13,
        "symbol": "301278",
        "name": "快可电子",
        "opened_trade_date": "2026-04-22",
        "entry_price": 44.0,
        "target_weight_pct": 8.0,
        "status": "closed",
        "theme": "半导体",
        "strategy_json": "[\"hotmoney\", \"leader\"]",
        "plan_json": "{\"symbol\": \"301278\", \"name\": \"快可电子\", \"display\": \"快可电子 (301278)\", \"theme\": \"半导体\", \"resonance_level\": \"A\", \"resonance_score\": 79.1, \"strategies\": [\"hotmoney\", \"leader\"], \"target_weight_pct\": 8.0, \"role\": \"follower\", \"thesis\": \"情绪阶段 ice / 题材热度排名 2 / 题材热度分 14.54\", \"sizing_meta\": {\"base_weight_pct\": 12.0, \"quality_multiplier\": 1.26, \"risk_discount\": 1.0, \"allowed_cap_pct\": 8.0}}",
        "created_at": "2026-04-22 13:07:32",
        "closed_trade_date": "2026-04-22",
        "exit_price": 44.0,
        "realized_return_pct": 0.0,
        "peak_return_pct": 0.0,
        "partial_exit_taken": 0,
        "lifecycle_state": "open"
      },
      {
        "id": 10,
        "symbol": "300584",
        "name": "海辰药业",
        "opened_trade_date": "2026-03-27",
        "entry_price": 45.18,
        "target_weight_pct": 8.0,
        "status": "closed",
        "theme": "医药",
        "strategy_json": "[\"hotmoney\", \"leader\"]",
        "plan_json": "{\"symbol\": \"300584\", \"name\": \"海辰药业\", \"display\": \"海辰药业 (300584)\", \"theme\": \"医药\", \"resonance_level\": \"A\", \"resonance_score\": 79.1, \"strategies\": [\"hotmoney\", \"leader\"], \"target_weight_pct\": 8.0, \"role\": \"follower\", \"thesis\": \"情绪阶段 ice / 题材热度排名 1 / 题材热度分 29.88\", \"sizing_meta\": {\"base_weight_pct\": 12.0, \"quality_multiplier\": 1.37, \"risk_discount\": 1.0, \"allowed_cap_pct\": 8.0}}",
        "created_at": "2026-03-27 14:57:31",
        "closed_trade_date": "2026-03-27",
        "exit_price": 45.18,
        "realized_return_pct": 0.0,
        "peak_return_pct": 0.0,
        "partial_exit_taken": 0,
        "lifecycle_state": "open"
      },
      {
        "id": 9,
        "symbol": "300584",
        "name": "海辰药业",
        "opened_trade_date": "2026-03-27",
        "entry_price": 45.18,
        "target_weight_pct": 8.0,
        "status": "closed",
        "theme": "医药",
        "strategy_json": "[\"hotmoney\", \"leader\"]",
        "plan_json": "{\"symbol\": \"300584\", \"name\": \"海辰药业\", \"display\": \"海辰药业 (300584)\", \"theme\": \"医药\", \"resonance_level\": \"A\", \"resonance_score\": 79.1, \"strategies\": [\"hotmoney\", \"leader\"], \"target_weight_pct\": 8.0, \"role\": \"follower\", \"thesis\": \"情绪阶段 ice / 题材热度排名 1 / 题材热度分 29.88\", \"sizing_meta\": {\"base_weight_pct\": 12.0, \"quality_multiplier\": 1.37, \"risk_discount\": 1.0, \"allowed_cap_pct\": 8.0}}",
        "created_at": "2026-03-27 14:45:15",
        "closed_trade_date": "2026-03-27",
        "exit_price": 45.18,
        "realized_return_pct": 0.0,
        "peak_return_pct": 0.0,
        "partial_exit_taken": 0,
        "lifecycle_state": "open"
      },
      {
        "id": 8,
        "symbol": "300584",
        "name": "海辰药业",
        "opened_trade_date": "2026-03-27",
        "entry_price": 45.18,
        "target_weight_pct": 8.0,
        "status": "closed",
        "theme": "医药",
        "strategy_json": "[\"hotmoney\", \"leader\"]",
        "plan_json": "{\"symbol\": \"300584\", \"name\": \"海辰药业\", \"display\": \"海辰药业 (300584)\", \"theme\": \"医药\", \"resonance_level\": \"A\", \"resonance_score\": 79.1, \"strategies\": [\"hotmoney\", \"leader\"], \"target_weight_pct\": 8.0, \"role\": \"follower\", \"thesis\": \"情绪阶段 ice / 题材热度排名 1 / 题材热度分 29.88\", \"sizing_meta\": {\"base_weight_pct\": 12.0, \"quality_multiplier\": 1.37, \"risk_discount\": 1.0, \"allowed_cap_pct\": 8.0}}",
        "created_at": "2026-03-27 14:45:00",
        "closed_trade_date": "2026-03-27",
        "exit_price": 45.18,
        "realized_return_pct": 0.0,
        "peak_return_pct": 0.0,
        "partial_exit_taken": 0,
        "lifecycle_state": "open"
      },
      {
        "id": 7,
        "symbol": "300584",
        "name": "海辰药业",
        "opened_trade_date": "2026-03-27",
        "entry_price": 45.18,
        "target_weight_pct": 8.0,
        "status": "closed",
        "theme": "医药",
        "strategy_json": "[\"hotmoney\", \"leader\"]",
        "plan_json": "{\"symbol\": \"300584\", \"name\": \"海辰药业\", \"display\": \"海辰药业 (300584)\", \"theme\": \"医药\", \"resonance_level\": \"A\", \"resonance_score\": 79.1, \"strategies\": [\"hotmoney\", \"leader\"], \"target_weight_pct\": 8.0, \"role\": \"follower\", \"thesis\": \"情绪阶段 ice / 题材热度排名 1 / 题材热度分 29.88\", \"sizing_meta\": {\"base_weight_pct\": 12.0, \"quality_multiplier\": 1.37, \"risk_discount\": 1.0, \"allowed_cap_pct\": 8.0}}",
        "created_at": "2026-03-27 14:40:43",
        "closed_trade_date": "2026-03-27",
        "exit_price": 45.18,
        "realized_return_pct": 0.0,
        "peak_return_pct": 0.0,
        "partial_exit_taken": 0,
        "lifecycle_state": "open"
      },
      {
        "id": 6,
        "symbol": "300584",
        "name": "海辰药业",
        "opened_trade_date": "2026-03-27",
        "entry_price": 45.18,
        "target_weight_pct": 12.0,
        "status": "closed",
        "theme": "医药",
        "strategy_json": "[\"hotmoney\", \"leader\"]",
        "plan_json": "{\"symbol\": \"300584\", \"name\": \"海辰药业\", \"display\": \"海辰药业 (300584)\", \"theme\": \"医药\", \"resonance_level\": \"A\", \"resonance_score\": 79.1, \"strategies\": [\"hotmoney\", \"leader\"], \"target_weight_pct\": 12, \"role\": \"follower\", \"thesis\": \"情绪阶段 ice / 题材热度排名 1 / 题材热度分 29.88\"}",
        "created_at": "2026-03-27 14:21:28",
        "closed_trade_date": "2026-03-27",
        "exit_price": 45.18,
        "realized_return_pct": 0.0,
        "peak_return_pct": 0.0,
        "partial_exit_taken": 0,
        "lifecycle_state": "open"
      },
      {
        "id": 4,
        "symbol": "301587",
        "name": "中瑞股份",
        "opened_trade_date": "2026-03-26",
        "entry_price": 27.03,
        "target_weight_pct": 12.0,
        "status": "closed",
        "theme": "电力设备",
        "strategy_json": "[\"hotmoney\", \"leader\"]",
        "plan_json": "{\"symbol\": \"301587\", \"name\": \"中瑞股份\", \"display\": \"中瑞股份 (301587)\", \"theme\": \"电力设备\", \"resonance_level\": \"A\", \"resonance_score\": 79.1, \"strategies\": [\"hotmoney\", \"leader\"], \"target_weight_pct\": 12, \"role\": \"follower\", \"thesis\": \"情绪阶段 ice / 题材热度排名 1 / 题材热度分 12.7\"}",
        "created_at": "2026-03-26 13:01:44",
        "closed_trade_date": "2026-03-26",
        "exit_price": 27.03,
        "realized_return_pct": 0.0,
        "peak_return_pct": 0.0,
        "partial_exit_taken": 0,
        "lifecycle_state": "open"
      },
      {
        "id": 3,
        "symbol": "301587",
        "name": "中瑞股份",
        "opened_trade_date": "2026-03-26",
        "entry_price": 27.03,
        "target_weight_pct": 12.0,
        "status": "closed",
        "theme": "电力设备",
        "strategy_json": "[\"hotmoney\", \"leader\"]",
        "plan_json": "{\"symbol\": \"301587\", \"name\": \"中瑞股份\", \"display\": \"中瑞股份 (301587)\", \"theme\": \"电力设备\", \"resonance_level\": \"A\", \"resonance_score\": 79.1, \"strategies\": [\"hotmoney\", \"leader\"], \"target_weight_pct\": 12, \"role\": \"follower\", \"thesis\": \"情绪阶段 ice / 题材热度排名 1 / 题材热度分 12.7\"}",
        "created_at": "2026-03-26 12:21:12",
        "closed_trade_date": "2026-03-26",
        "exit_price": 27.03,
        "realized_return_pct": 0.0,
        "peak_return_pct": 0.0,
        "partial_exit_taken": 0,
        "lifecycle_state": "open"
      },
      {
        "id": 2,
        "symbol": "000001",
        "name": "深量科技",
        "opened_trade_date": "2026-03-25",
        "entry_price": 18.23,
        "target_weight_pct": 8.0,
        "status": "closed",
        "theme": "算力",
        "strategy_json": "[\"hotmoney\", \"leader\"]",
        "plan_json": "{\"symbol\": \"000001\", \"name\": \"深量科技\", \"display\": \"深量科技 (000001)\", \"theme\": \"算力\", \"resonance_level\": \"A\", \"resonance_score\": 100.0, \"strategies\": [\"hotmoney\", \"leader\"], \"target_weight_pct\": 8, \"role\": \"mainline_leader\", \"thesis\": \"情绪阶段 ice / 题材热度排名 2 / 题材热度分 2.52\"}",
        "created_at": "2026-03-25 13:03:14",
        "closed_trade_date": "2026-03-25",
        "exit_price": 18.23,
        "realized_return_pct": 0.0,
        "peak_return_pct": 0.0,
        "partial_exit_taken": 0,
        "lifecycle_state": "open"
      },
      {
        "id": 1,
        "symbol": "000004",
        "name": "盛景智能",
        "opened_trade_date": "2026-03-25",
        "entry_price": 22.11,
        "target_weight_pct": 12.0,
        "status": "closed",
        "theme": "机器人",
        "strategy_json": "[\"hotmoney\", \"leader\"]",
        "plan_json": "{\"symbol\": \"000004\", \"name\": \"盛景智能\", \"display\": \"盛景智能 (000004)\", \"theme\": \"机器人\", \"resonance_level\": \"A\", \"resonance_score\": 100.0, \"strategies\": [\"hotmoney\", \"leader\"], \"target_weight_pct\": 12, \"role\": \"mainline_leader\", \"thesis\": \"情绪阶段 ice / 题材热度排名 1 / 题材热度分 2.62\"}",
        "created_at": "2026-03-25 13:03:14",
        "closed_trade_date": "2026-04-22",
        "exit_price": 22.11,
        "realized_return_pct": 0.0,
        "peak_return_pct": 0.0,
        "partial_exit_taken": 0,
        "lifecycle_state": "open"
      }
    ],
    "recent_trades": [
      {
        "id": 28,
        "trade_date": "2026-04-22",
        "symbol": "301278",
        "name": "快可电子",
        "side": "buy",
        "price": 44.0,
        "weight_pct": 8.0,
        "note": "paper_entry",
        "created_at": "2026-04-22 13:14:28"
      },
      {
        "id": 27,
        "trade_date": "2026-04-22",
        "symbol": "301278",
        "name": "快可电子",
        "side": "sell",
        "price": 44.0,
        "weight_pct": 8.0,
        "note": "paper_riskmode_exit",
        "created_at": "2026-04-22 13:14:28"
      },
      {
        "id": 26,
        "trade_date": "2026-04-22",
        "symbol": "301278",
        "name": "快可电子",
        "side": "buy",
        "price": 44.0,
        "weight_pct": 8.0,
        "note": "paper_entry",
        "created_at": "2026-04-22 13:10:33"
      },
      {
        "id": 25,
        "trade_date": "2026-04-22",
        "symbol": "301278",
        "name": "快可电子",
        "side": "sell",
        "price": 44.0,
        "weight_pct": 8.0,
        "note": "paper_riskmode_exit",
        "created_at": "2026-04-22 13:10:33"
      },
      {
        "id": 24,
        "trade_date": "2026-04-22",
        "symbol": "301278",
        "name": "快可电子",
        "side": "buy",
        "price": 44.0,
        "weight_pct": 8.0,
        "note": "paper_entry",
        "created_at": "2026-04-22 13:08:23"
      },
      {
        "id": 23,
        "trade_date": "2026-04-22",
        "symbol": "301278",
        "name": "快可电子",
        "side": "sell",
        "price": 44.0,
        "weight_pct": 8.0,
        "note": "paper_riskmode_exit",
        "created_at": "2026-04-22 13:08:23"
      },
      {
        "id": 22,
        "trade_date": "2026-04-22",
        "symbol": "301278",
        "name": "快可电子",
        "side": "buy",
        "price": 44.0,
        "weight_pct": 8.0,
        "note": "paper_entry",
        "created_at": "2026-04-22 13:07:32"
      },
      {
        "id": 21,
        "trade_date": "2026-04-22",
        "symbol": "000004",
        "name": "盛景智能",
        "side": "buy",
        "price": 22.11,
        "weight_pct": 8.0,
        "note": "paper_entry",
        "created_at": "2026-04-22 00:31:57"
      },
      {
        "id": 20,
        "trade_date": "2026-04-22",
        "symbol": "000004",
        "name": "盛景智能",
        "side": "sell",
        "price": 22.11,
        "weight_pct": 12.0,
        "note": "paper_time_exit",
        "created_at": "2026-04-22 00:31:57"
      },
      {
        "id": 19,
        "trade_date": "2026-03-27",
        "symbol": "300584",
        "name": "海辰药业",
        "side": "buy",
        "price": 45.18,
        "weight_pct": 12.0,
        "note": "paper_entry",
        "created_at": "2026-03-27 15:31:35"
      },
      {
        "id": 18,
        "trade_date": "2026-03-27",
        "symbol": "300584",
        "name": "海辰药业",
        "side": "sell",
        "price": 45.18,
        "weight_pct": 8.0,
        "note": "paper_riskmode_exit",
        "created_at": "2026-03-27 15:31:35"
      },
      {
        "id": 17,
        "trade_date": "2026-03-27",
        "symbol": "300584",
        "name": "海辰药业",
        "side": "buy",
        "price": 45.18,
        "weight_pct": 8.0,
        "note": "paper_entry",
        "created_at": "2026-03-27 14:57:31"
      },
      {
        "id": 16,
        "trade_date": "2026-03-27",
        "symbol": "300584",
        "name": "海辰药业",
        "side": "sell",
        "price": 45.18,
        "weight_pct": 8.0,
        "note": "paper_riskmode_exit",
        "created_at": "2026-03-27 14:57:31"
      },
      {
        "id": 15,
        "trade_date": "2026-03-27",
        "symbol": "300584",
        "name": "海辰药业",
        "side": "buy",
        "price": 45.18,
        "weight_pct": 8.0,
        "note": "paper_entry",
        "created_at": "2026-03-27 14:45:15"
      },
      {
        "id": 14,
        "trade_date": "2026-03-27",
        "symbol": "300584",
        "name": "海辰药业",
        "side": "sell",
        "price": 45.18,
        "weight_pct": 8.0,
        "note": "paper_riskmode_exit",
        "created_at": "2026-03-27 14:45:15"
      },
      {
        "id": 13,
        "trade_date": "2026-03-27",
        "symbol": "300584",
        "name": "海辰药业",
        "side": "buy",
        "price": 45.18,
        "weight_pct": 8.0,
        "note": "paper_entry",
        "created_at": "2026-03-27 14:45:00"
      },
      {
        "id": 12,
        "trade_date": "2026-03-27",
        "symbol": "300584",
        "name": "海辰药业",
        "side": "sell",
        "price": 45.18,
        "weight_pct": 8.0,
        "note": "paper_riskmode_exit",
        "created_at": "2026-03-27 14:45:00"
      },
      {
        "id": 11,
        "trade_date": "2026-03-27",
        "symbol": "300584",
        "name": "海辰药业",
        "side": "buy",
        "price": 45.18,
        "weight_pct": 8.0,
        "note": "paper_entry",
        "created_at": "2026-03-27 14:40:43"
      },
      {
        "id": 10,
        "trade_date": "2026-03-27",
        "symbol": "300584",
        "name": "海辰药业",
        "side": "sell",
        "price": 45.18,
        "weight_pct": 12.0,
        "note": "paper_riskmode_exit",
        "created_at": "2026-03-27 14:40:43"
      },
      {
        "id": 9,
        "trade_date": "2026-03-27",
        "symbol": "300584",
        "name": "海辰药业",
        "side": "buy",
        "price": 45.18,
        "weight_pct": 12.0,
        "note": "paper_entry",
        "created_at": "2026-03-27 14:21:28"
      }
    ]
  },
  "strategy_portfolios": {
    "enabled": true,
    "summary": {
      "portfolio_count": 3,
      "initial_capital_per_portfolio": 1000000.0,
      "items": [
        {
          "id": 1,
          "portfolio_key": "mainline_leader",
          "name": "主线龙头组合",
          "initial_capital": 1000000.0,
          "cash": 1000000.0,
          "nav": 1000000.0,
          "config_json": "{\"key\": \"mainline_leader\", \"name\": \"主线龙头组合\", \"description\": \"只做主线龙头与前排核心，频率低，强调确定性。\", \"styles\": {\"roles\": [\"mainline_leader\", \"frontline_core\"], \"levels\": [\"A\", \"B\"], \"min_strategy_count\": 1, \"max_positions\": 3, \"cash_buffer_pct\": 28}}",
          "created_at": "2026-03-27 14:21:27",
          "updated_at": "2026-04-22 13:14:28",
          "display_name": "主线龙头组合",
          "description": "只做主线龙头与前排核心，频率低，强调确定性。",
          "styles": {
            "roles": [
              "mainline_leader",
              "frontline_core"
            ],
            "levels": [
              "A",
              "B"
            ],
            "min_strategy_count": 1,
            "max_positions": 3,
            "cash_buffer_pct": 28
          },
          "positions": [],
          "recent_trades": [],
          "nav_history": [
            {
              "id": 28,
              "portfolio_key": "mainline_leader",
              "trade_date": "2026-04-22",
              "nav": 1000000.0,
              "cash": 1000000.0,
              "market_value": 0.0,
              "note": "auto_rebalance",
              "created_at": "2026-04-22 13:14:28"
            },
            {
              "id": 25,
              "portfolio_key": "mainline_leader",
              "trade_date": "2026-04-22",
              "nav": 1000000.0,
              "cash": 1000000.0,
              "market_value": 0.0,
              "note": "auto_rebalance",
              "created_at": "2026-04-22 13:10:18"
            },
            {
              "id": 22,
              "portfolio_key": "mainline_leader",
              "trade_date": "2026-04-22",
              "nav": 1000000.0,
              "cash": 1000000.0,
              "market_value": 0.0,
              "note": "auto_rebalance",
              "created_at": "2026-04-22 13:08:57"
            },
            {
              "id": 19,
              "portfolio_key": "mainline_leader",
              "trade_date": "2026-04-22",
              "nav": 1000000.0,
              "cash": 1000000.0,
              "market_value": 0.0,
              "note": "auto_rebalance",
              "created_at": "2026-04-22 00:35:25"
            },
            {
              "id": 16,
              "portfolio_key": "mainline_leader",
              "trade_date": "2026-04-22",
              "nav": 1000000.0,
              "cash": 1000000.0,
              "market_value": 0.0,
              "note": "auto_rebalance",
              "created_at": "2026-04-22 00:34:01"
            },
            {
              "id": 13,
              "portfolio_key": "mainline_leader",
              "trade_date": "2026-03-27",
              "nav": 1000000.0,
              "cash": 1000000.0,
              "market_value": 0.0,
              "note": "auto_rebalance",
              "created_at": "2026-03-27 15:21:25"
            },
            {
              "id": 10,
              "portfolio_key": "mainline_leader",
              "trade_date": "2026-03-27",
              "nav": 1000000.0,
              "cash": 1000000.0,
              "market_value": 0.0,
              "note": "auto_rebalance",
              "created_at": "2026-03-27 14:57:58"
            },
            {
              "id": 7,
              "portfolio_key": "mainline_leader",
              "trade_date": "2026-03-27",
              "nav": 1000000.0,
              "cash": 1000000.0,
              "market_value": 0.0,
              "note": "auto_rebalance",
              "created_at": "2026-03-27 14:45:40"
            },
            {
              "id": 4,
              "portfolio_key": "mainline_leader",
              "trade_date": "2026-03-27",
              "nav": 1000000.0,
              "cash": 1000000.0,
              "market_value": 0.0,
              "note": "auto_rebalance",
              "created_at": "2026-03-27 14:41:15"
            },
            {
              "id": 1,
              "portfolio_key": "mainline_leader",
              "trade_date": "2026-03-27",
              "nav": 1000000.0,
              "cash": 1000000.0,
              "market_value": 0.0,
              "note": "auto_rebalance",
              "created_at": "2026-03-27 14:21:30"
            }
          ],
          "position_count": 0,
          "total_return_pct": 0.0
        },
        {
          "id": 2,
          "portfolio_key": "double_resonance",
          "name": "双确认高共振组合",
          "initial_capital": 1000000.0,
          "cash": 1000000.0,
          "nav": 1000000.0,
          "config_json": "{\"key\": \"double_resonance\", \"name\": \"双确认高共振组合\", \"description\": \"至少双策略共识，优先 A/B 级共振，偏胜率优先。\", \"styles\": {\"roles\": [\"mainline_leader\", \"frontline_core\", \"secondary_rotation\"], \"levels\": [\"A\", \"B\"], \"min_strategy_count\": 2, \"max_positions\": 4, \"cash_buffer_pct\": 20}}",
          "created_at": "2026-03-27 14:21:27",
          "updated_at": "2026-04-22 13:14:28",
          "display_name": "双确认高共振组合",
          "description": "至少双策略共识，优先 A/B 级共振，偏胜率优先。",
          "styles": {
            "roles": [
              "mainline_leader",
              "frontline_core",
              "secondary_rotation"
            ],
            "levels": [
              "A",
              "B"
            ],
            "min_strategy_count": 2,
            "max_positions": 4,
            "cash_buffer_pct": 20
          },
          "positions": [],
          "recent_trades": [],
          "nav_history": [
            {
              "id": 29,
              "portfolio_key": "double_resonance",
              "trade_date": "2026-04-22",
              "nav": 1000000.0,
              "cash": 1000000.0,
              "market_value": 0.0,
              "note": "auto_rebalance",
              "created_at": "2026-04-22 13:14:28"
            },
            {
              "id": 26,
              "portfolio_key": "double_resonance",
              "trade_date": "2026-04-22",
              "nav": 1000000.0,
              "cash": 1000000.0,
              "market_value": 0.0,
              "note": "auto_rebalance",
              "created_at": "2026-04-22 13:10:18"
            },
            {
              "id": 23,
              "portfolio_key": "double_resonance",
              "trade_date": "2026-04-22",
              "nav": 1000000.0,
              "cash": 1000000.0,
              "market_value": 0.0,
              "note": "auto_rebalance",
              "created_at": "2026-04-22 13:08:57"
            },
            {
              "id": 20,
              "portfolio_key": "double_resonance",
              "trade_date": "2026-04-22",
              "nav": 1000000.0,
              "cash": 1000000.0,
              "market_value": 0.0,
              "note": "auto_rebalance",
              "created_at": "2026-04-22 00:35:25"
            },
            {
              "id": 17,
              "portfolio_key": "double_resonance",
              "trade_date": "2026-04-22",
              "nav": 1000000.0,
              "cash": 1000000.0,
              "market_value": 0.0,
              "note": "auto_rebalance",
              "created_at": "2026-04-22 00:34:01"
            },
            {
              "id": 14,
              "portfolio_key": "double_resonance",
              "trade_date": "2026-03-27",
              "nav": 1000000.0,
              "cash": 1000000.0,
              "market_value": 0.0,
              "note": "auto_rebalance",
              "created_at": "2026-03-27 15:21:25"
            },
            {
              "id": 11,
              "portfolio_key": "double_resonance",
              "trade_date": "2026-03-27",
              "nav": 1000000.0,
              "cash": 1000000.0,
              "market_value": 0.0,
              "note": "auto_rebalance",
              "created_at": "2026-03-27 14:57:58"
            },
            {
              "id": 8,
              "portfolio_key": "double_resonance",
              "trade_date": "2026-03-27",
              "nav": 1000000.0,
              "cash": 1000000.0,
              "market_value": 0.0,
              "note": "auto_rebalance",
              "created_at": "2026-03-27 14:45:40"
            },
            {
              "id": 5,
              "portfolio_key": "double_resonance",
              "trade_date": "2026-03-27",
              "nav": 1000000.0,
              "cash": 1000000.0,
              "market_value": 0.0,
              "note": "auto_rebalance",
              "created_at": "2026-03-27 14:41:15"
            },
            {
              "id": 2,
              "portfolio_key": "double_resonance",
              "trade_date": "2026-03-27",
              "nav": 1000000.0,
              "cash": 1000000.0,
              "market_value": 0.0,
              "note": "auto_rebalance",
              "created_at": "2026-03-27 14:21:30"
            }
          ],
          "position_count": 0,
          "total_return_pct": 0.0
        },
        {
          "id": 3,
          "portfolio_key": "defensive_rotation",
          "name": "防守轮动组合",
          "initial_capital": 1000000.0,
          "cash": 1000000.0,
          "nav": 1000000.0,
          "config_json": "{\"key\": \"defensive_rotation\", \"name\": \"防守轮动组合\", \"description\": \"偏防守，控制回撤，只做高质量轮动与低风险暴露。\", \"styles\": {\"roles\": [\"frontline_core\", \"secondary_rotation\", \"follower\"], \"levels\": [\"A\", \"B\", \"C\"], \"min_strategy_count\": 1, \"max_positions\": 5, \"cash_buffer_pct\": 35}}",
          "created_at": "2026-03-27 14:21:27",
          "updated_at": "2026-04-22 13:14:28",
          "display_name": "防守轮动组合",
          "description": "偏防守，控制回撤，只做高质量轮动与低风险暴露。",
          "styles": {
            "roles": [
              "frontline_core",
              "secondary_rotation",
              "follower"
            ],
            "levels": [
              "A",
              "B",
              "C"
            ],
            "min_strategy_count": 1,
            "max_positions": 5,
            "cash_buffer_pct": 35
          },
          "positions": [],
          "recent_trades": [],
          "nav_history": [
            {
              "id": 30,
              "portfolio_key": "defensive_rotation",
              "trade_date": "2026-04-22",
              "nav": 1000000.0,
              "cash": 1000000.0,
              "market_value": 0.0,
              "note": "auto_rebalance",
              "created_at": "2026-04-22 13:14:28"
            },
            {
              "id": 27,
              "portfolio_key": "defensive_rotation",
              "trade_date": "2026-04-22",
              "nav": 1000000.0,
              "cash": 1000000.0,
              "market_value": 0.0,
              "note": "auto_rebalance",
              "created_at": "2026-04-22 13:10:18"
            },
            {
              "id": 24,
              "portfolio_key": "defensive_rotation",
              "trade_date": "2026-04-22",
              "nav": 1000000.0,
              "cash": 1000000.0,
              "market_value": 0.0,
              "note": "auto_rebalance",
              "created_at": "2026-04-22 13:08:57"
            },
            {
              "id": 21,
              "portfolio_key": "defensive_rotation",
              "trade_date": "2026-04-22",
              "nav": 1000000.0,
              "cash": 1000000.0,
              "market_value": 0.0,
              "note": "auto_rebalance",
              "created_at": "2026-04-22 00:35:25"
            },
            {
              "id": 18,
              "portfolio_key": "defensive_rotation",
              "trade_date": "2026-04-22",
              "nav": 1000000.0,
              "cash": 1000000.0,
              "market_value": 0.0,
              "note": "auto_rebalance",
              "created_at": "2026-04-22 00:34:01"
            },
            {
              "id": 15,
              "portfolio_key": "defensive_rotation",
              "trade_date": "2026-03-27",
              "nav": 1000000.0,
              "cash": 1000000.0,
              "market_value": 0.0,
              "note": "auto_rebalance",
              "created_at": "2026-03-27 15:21:25"
            },
            {
              "id": 12,
              "portfolio_key": "defensive_rotation",
              "trade_date": "2026-03-27",
              "nav": 1000000.0,
              "cash": 1000000.0,
              "market_value": 0.0,
              "note": "auto_rebalance",
              "created_at": "2026-03-27 14:57:58"
            },
            {
              "id": 9,
              "portfolio_key": "defensive_rotation",
              "trade_date": "2026-03-27",
              "nav": 1000000.0,
              "cash": 1000000.0,
              "market_value": 0.0,
              "note": "auto_rebalance",
              "created_at": "2026-03-27 14:45:40"
            },
            {
              "id": 6,
              "portfolio_key": "defensive_rotation",
              "trade_date": "2026-03-27",
              "nav": 1000000.0,
              "cash": 1000000.0,
              "market_value": 0.0,
              "note": "auto_rebalance",
              "created_at": "2026-03-27 14:41:15"
            },
            {
              "id": 3,
              "portfolio_key": "defensive_rotation",
              "trade_date": "2026-03-27",
              "nav": 1000000.0,
              "cash": 1000000.0,
              "market_value": 0.0,
              "note": "auto_rebalance",
              "created_at": "2026-03-27 14:21:30"
            }
          ],
          "position_count": 0,
          "total_return_pct": 0.0
        }
      ]
    }
  },
  "risk_gate": {
    "market_stage": "ice",
    "risk_mode": "defensive_probe",
    "execution_policy": "paper_only",
    "no_trade": false,
    "risk_budget_pct": 20.0,
    "remaining_risk_budget_pct": 12.0,
    "risk_profile": {
      "risk_mode": "defensive_probe",
      "market_stage": "ice",
      "limits": {
        "single_position_cap_pct": 8.0,
        "single_theme_cap_pct": 12.0,
        "single_strategy_cap_pct": 14.0,
        "daily_new_exposure_cap_pct": 20.0
      },
      "risk_discount": 1.0,
      "cooldown": false,
      "recent_negative_streak": 0,
      "historical_stage_avg_return_1d": 1.12,
      "historical_stage_win_rate_1d_pct": 100.0,
      "strategy_governor": {
        "history_signal_count": 200,
        "trade_count": 0,
        "enabled_strategies": [],
        "frozen_strategies": [],
        "items": [],
        "notes": []
      },
      "candidate_diagnostics": [
        {
          "symbol": "301278",
          "theme": "半导体",
          "avg_strategy_edge_1d": 1.12,
          "symbol_avg_return_1d": null,
          "symbol_win_rate_1d_pct": null,
          "strategy_weight_multiplier": 1.0,
          "blocked_by_governor": false,
          "quality_multiplier": 1.37
        }
      ],
      "notes": []
    },
    "notes": [
      "情绪冰点，以轻仓试错为主。",
      "优先保留高共振候选，不做弱共振扩散交易。",
      "当前实验层推荐参数集：baseline",
      "avg_score=None, win_rate=None%",
      "剩余未使用风险预算 12.0% 。"
    ]
  },
  "report": {
    "trade_date": "2026-04-22",
    "market": {
      "trade_date": "2026-04-22",
      "market_sentiment_stage": "ice",
      "limit_up_count": 50,
      "limit_down_count": 0,
      "broken_board_rate": 0.0,
      "highest_board": 0,
      "notes": [
        "涨停家数 50 / Limit-up count 50",
        "跌停家数 0 / Limit-down count 0",
        "最高连板 0 / Highest board 0",
        "炸板率 0.0% / Broken-board rate 0.0%"
      ]
    },
    "top_signals": [
      {
        "strategy": "hotmoney",
        "symbol": "301278",
        "name": "快可电子",
        "score": 64.9,
        "risk_level": "medium",
        "reasons": [
          "游资净买额 0.0 百万",
          "量比 5.24",
          "叙事强度 0.5",
          "题材归属 半导体"
        ],
        "entry_note": "优先关注与主线题材共振、且次日有承接预期的标的。",
        "exit_note": "若游资次日无溢价或板块分歧扩大，降低仓位或止盈。",
        "invalidation_note": "若席位行为与题材热度脱钩，则跟踪逻辑弱化。",
        "theme": "半导体",
        "secondary_theme": "",
        "concepts": [],
        "resonance_score": 79.1,
        "resonance_level": "A",
        "resonance_role": "follower",
        "resonance_reasons": [
          "情绪阶段 ice",
          "题材热度排名 2",
          "题材热度分 14.54",
          "共振角色 follower",
          "属于当前主线题材"
        ]
      },
      {
        "strategy": "leader",
        "symbol": "301278",
        "name": "快可电子",
        "score": 56.9,
        "risk_level": "medium",
        "reasons": [
          "连板高度 0",
          "竞价强度 0.5",
          "封单强度 0.5",
          "题材归属 半导体"
        ],
        "entry_note": "关注分歧后的承接与回封，不追情绪极致一致。",
        "exit_note": "次日弱转强失败、放量走弱或核心题材退潮时考虑退出。",
        "invalidation_note": "若高开低走且失去板块带动性，则该信号失效。",
        "theme": "半导体",
        "secondary_theme": "",
        "concepts": [],
        "resonance_score": 79.1,
        "resonance_level": "A",
        "resonance_role": "follower",
        "resonance_reasons": [
          "情绪阶段 ice",
          "题材热度排名 2",
          "题材热度分 14.54",
          "共振角色 follower",
          "属于当前主线题材"
        ]
      },
      {
        "strategy": "leader",
        "symbol": "301629",
        "name": "矽电股份",
        "score": 61.1,
        "risk_level": "medium",
        "reasons": [
          "连板高度 0",
          "竞价强度 0.5",
          "封单强度 0.5",
          "题材归属 电子"
        ],
        "entry_note": "关注分歧后的承接与回封，不追情绪极致一致。",
        "exit_note": "次日弱转强失败、放量走弱或核心题材退潮时考虑退出。",
        "invalidation_note": "若高开低走且失去板块带动性，则该信号失效。",
        "theme": "电子",
        "secondary_theme": "半导体",
        "concepts": [
          "电子",
          "半导体",
          "半导体设备",
          "百元股",
          "专精特新",
          "半导体概念",
          "华为概念"
        ],
        "resonance_score": 76.7,
        "resonance_level": "B",
        "resonance_role": "follower",
        "resonance_reasons": [
          "情绪阶段 ice",
          "题材热度排名 1",
          "题材热度分 28.1",
          "共振角色 follower",
          "属于当前主线题材"
        ]
      },
      {
        "strategy": "hotmoney",
        "symbol": "301607",
        "name": "富特科技",
        "score": 69.1,
        "risk_level": "medium",
        "reasons": [
          "游资净买额 0.0 百万",
          "量比 5.66",
          "叙事强度 0.5",
          "题材归属 汽车"
        ],
        "entry_note": "优先关注与主线题材共振、且次日有承接预期的标的。",
        "exit_note": "若游资次日无溢价或板块分歧扩大，降低仓位或止盈。",
        "invalidation_note": "若席位行为与题材热度脱钩，则跟踪逻辑弱化。",
        "theme": "汽车",
        "secondary_theme": "汽车零部件",
        "concepts": [
          "汽车",
          "汽车零部件",
          "汽车电子电气系统",
          "2025年报预增",
          "百日新高",
          "历史新高",
          "近期新高",
          "专精特新",
          "小米汽车",
          "第三代半导体",
          "新能源车",
          "充电桩"
        ],
        "resonance_score": 68.3,
        "resonance_level": "B",
        "resonance_role": "follower",
        "resonance_reasons": [
          "情绪阶段 ice",
          "题材热度排名 4",
          "题材热度分 6.64",
          "共振角色 follower"
        ]
      },
      {
        "strategy": "hotmoney",
        "symbol": "300698",
        "name": "万马科技",
        "score": 69.3,
        "risk_level": "medium",
        "reasons": [
          "游资净买额 0.0 百万",
          "量比 5.68",
          "叙事强度 0.5",
          "题材归属 通信"
        ],
        "entry_note": "优先关注与主线题材共振、且次日有承接预期的标的。",
        "exit_note": "若游资次日无溢价或板块分歧扩大，降低仓位或止盈。",
        "invalidation_note": "若席位行为与题材热度脱钩，则跟踪逻辑弱化。",
        "theme": "通信",
        "secondary_theme": "通信设备",
        "concepts": [
          "通信",
          "通信设备",
          "通信网络设备及器件",
          "专精特新",
          "通信技术",
          "DeepSeek概念",
          "英伟达概念",
          "液冷概念",
          "算力概念",
          "数据中心",
          "互联医疗",
          "车联网(车路云)",
          "无人驾驶",
          "5G概念",
          "物联网"
        ],
        "resonance_score": 66.4,
        "resonance_level": "B",
        "resonance_role": "follower",
        "resonance_reasons": [
          "情绪阶段 ice",
          "题材热度排名 5",
          "题材热度分 6.54",
          "共振角色 follower"
        ]
      },
      {
        "strategy": "leader",
        "symbol": "688530",
        "name": "欧莱新材",
        "score": 62.2,
        "risk_level": "medium",
        "reasons": [
          "连板高度 0",
          "竞价强度 0.5",
          "封单强度 0.5",
          "题材归属 电子"
        ],
        "entry_note": "关注分歧后的承接与回封，不追情绪极致一致。",
        "exit_note": "次日弱转强失败、放量走弱或核心题材退潮时考虑退出。",
        "invalidation_note": "若高开低走且失去板块带动性，则该信号失效。",
        "theme": "电子",
        "secondary_theme": "半导体",
        "concepts": [
          "电子",
          "半导体",
          "半导体材料",
          "昨日高振幅",
          "昨日高换手",
          "专精特新",
          "复合集流体",
          "半导体概念",
          "HJT电池",
          "光伏概念",
          "新材料"
        ],
        "resonance_score": 65.7,
        "resonance_level": "B",
        "resonance_role": "noise",
        "resonance_reasons": [
          "情绪阶段 ice",
          "题材热度排名 1",
          "题材热度分 28.1",
          "共振角色 noise",
          "属于当前主线题材"
        ]
      },
      {
        "strategy": "leader",
        "symbol": "688820",
        "name": "C盛合",
        "score": 100.0,
        "risk_level": "medium",
        "reasons": [
          "连板高度 0",
          "竞价强度 0.5",
          "封单强度 0.5",
          "题材归属 电子"
        ],
        "entry_note": "关注分歧后的承接与回封，不追情绪极致一致。",
        "exit_note": "次日弱转强失败、放量走弱或核心题材退潮时考虑退出。",
        "invalidation_note": "若高开低走且失去板块带动性，则该信号失效。",
        "theme": "电子",
        "secondary_theme": "半导体",
        "concepts": [
          "电子",
          "半导体",
          "集成电路制造",
          "先进封装",
          "半导体概念",
          "次新股"
        ],
        "resonance_score": 63.7,
        "resonance_level": "C",
        "resonance_role": "noise",
        "resonance_reasons": [
          "情绪阶段 ice",
          "题材热度排名 1",
          "题材热度分 28.1",
          "共振角色 noise",
          "属于当前主线题材"
        ]
      },
      {
        "strategy": "leader",
        "symbol": "300890",
        "name": "翔丰华",
        "score": 60.7,
        "risk_level": "medium",
        "reasons": [
          "连板高度 0",
          "竞价强度 0.5",
          "封单强度 0.5",
          "题材归属 电力设备"
        ],
        "entry_note": "关注分歧后的承接与回封，不追情绪极致一致。",
        "exit_note": "次日弱转强失败、放量走弱或核心题材退潮时考虑退出。",
        "invalidation_note": "若高开低走且失去板块带动性，则该信号失效。",
        "theme": "电力设备",
        "secondary_theme": "电池",
        "concepts": [
          "电力设备",
          "电池",
          "电池化学品",
          "百日新高",
          "近期新高",
          "转债标的",
          "电池技术",
          "碳基材料",
          "储能概念",
          "钠离子电池",
          "固态电池",
          "新能源车",
          "特斯拉概念",
          "石墨烯",
          "锂电池概念",
          "深圳特区"
        ],
        "resonance_score": 55.5,
        "resonance_level": "C",
        "resonance_role": "follower",
        "resonance_reasons": [
          "情绪阶段 ice",
          "题材热度排名 11",
          "题材热度分 3.87",
          "共振角色 follower"
        ]
      }
    ],
    "summary_cn": "2026-04-22 市场处于冰点阶段，涨停 50 家，跌停 0 家，最高连板 0。当前优先关注强共振候选：快可电子(301278)、矽电股份(301629)、富特科技(301607)。其中优先看主线题材内的主线龙头/前排核心，弱共振或噪声信号如 暂无明显回避标的 更适合观察而非追击。整体仍以盘后研究、次日验证和轻量试错为主，不建议直接当作全自动执行信号。",
    "summary_en": "On 2026-04-22, the market is in ice stage. There are 50 limit-up stocks, 0 limit-down stocks, and the highest board is 0. Priority goes to high-resonance names: 快可电子(301278)、矽电股份(301629)、富特科技(301607). Prefer mainline leaders/frontline core setups, while weaker names such as 暂无明显回避标的 are better treated as watch-only. Use this as a research and next-day validation framework, not a fully automated execution trigger.",
    "mainline_themes": [
      "半导体",
      "电子",
      "汽车"
    ],
    "focus_candidates": [
      "快可电子(301278)",
      "矽电股份(301629)",
      "富特科技(301607)"
    ],
    "observe_candidates": [
      "C盛合(688820)",
      "翔丰华(300890)"
    ],
    "avoid_candidates": [],
    "tomorrow_plan": [
      "优先盯住主线题材：半导体、电子。",
      "重点跟踪强共振候选的竞价、承接和回封质量：快可电子(301278)、矽电股份(301629)。",
      "情绪仍偏冰点，适合轻仓试错，不宜把弱共振信号当成进攻主仓。"
    ]
  }
}